docs/__init__.py
docs/chart.py
docs/conf.py
examples/__init__.py
gviz_data_table/__init__.py
gviz_data_table/cell.py
gviz_data_table/column.py
gviz_data_table/encoder.py
gviz_data_table/table.py
gviz_data_table-2.0.0.dist-info/METADATA
gviz_data_table-2.0.0.dist-info/WHEEL
gviz_data_table-2.0.0.dist-info/top_level.txt
gviz_data_table-2.0.0.dist-info/RECORD
