Metadata-Version: 2.1
Name: gviz_data_table
Version: 2.0.0
Summary: Python API for Google Visualization
Author: Charlie Clark
Author-email: charlie.clark@clark-consulting.eu
License: BSD
Project-URL: Documentation, https://gviz-data-table.readthedocs.io/en/stable/
Project-URL: Source, https://foss.heptapod.net/openpyxl/gviz-data-table
Project-URL: Tracker, https://foss.heptapod.net/openpyxl/gviz-data-table/-/issues
Keywords: charting graph Google Visualisation
Classifier: Development Status :: 5 - Production/Stable
Classifier: Environment :: Web Environment
Classifier: Intended Audience :: Developers
Classifier: License :: OSI Approved :: BSD License
Classifier: Programming Language :: Python :: 3.8
Classifier: Programming Language :: Python :: 3.9
Classifier: Programming Language :: Python :: 3.10
Classifier: Programming Language :: Python :: 3.11
Requires-Python: >=3.8
